README.md
setup.py
iosxr_grpc/__init__.py
iosxr_grpc/cisco_grpc_client.py
iosxr_grpc/ems_grpc_pb2.py
iosxr_grpc/json_format.py
iosxr_grpc/telemetry_pb2.py
iosxr_grpc.egg-info/PKG-INFO
iosxr_grpc.egg-info/SOURCES.txt
iosxr_grpc.egg-info/dependency_links.txt
iosxr_grpc.egg-info/not-zip-safe
iosxr_grpc.egg-info/requires.txt
iosxr_grpc.egg-info/top_level.txt