Metadata-Version: 1.0
Name: iosxr-grpc
Version: 1.3
Summary: gRPC library for IOS-XR > 6.1.1
Home-page: https://github.com/cisco-grpc-connection-libs/ios-xr-grpc-python
Author: Karthik Kumaravel
Author-email: UNKNOWN
License: UNKNOWN
Platform: UNKNOWN
